kubejobs/__init__.py
kubejobs/fetch_logs_of_failed_pods.py
kubejobs/jobs.py
kubejobs/manage_user_jobs.py
kubejobs/pods.py
kubejobs/wandb_monitor.py
kubejobs/wandb_pod_info.py
kubejobs/wandb_pod_injection.py
kubejobs/web_job_info.py
kubejobs/web_pod_info.py
kubejobs/examples/__init__.py
kubejobs/examples/example_disk_defined_job.py
kubejobs/examples/example_docker_in_docker_job.py
kubejobs/examples/example_interactive_job.py
kubejobs/examples/example_job.py
kubejobs/examples/example_pod.py
kubejobs/examples/example_pv.py
kubejobs/examples/example_pvc.py
kubejobs/examples/example_storage_write_read.py
kubejobs-0.4.8.dist-info/LICENSE
kubejobs-0.4.8.dist-info/METADATA
kubejobs-0.4.8.dist-info/WHEEL
kubejobs-0.4.8.dist-info/top_level.txt
kubejobs-0.4.8.dist-info/RECORD
