Metadata-Version: 2.1
Name: kubejobs
Version: 0.4.8
Summary: A Python library for creating and running Kubernetes Jobs
Home-page: https://github.com/AntreasAntoniou/kubejobs
Author: Antreas Antoniou
Author-email: iam@antreas.io
Classifier: Development Status :: 3 - Alpha
Classifier: Intended Audience :: Developers
Classifier: License :: OSI Approved :: MIT License
Classifier: Operating System :: OS Independent
Classifier: Programming Language :: Python
Classifier: Programming Language :: Python :: 3
Classifier: Programming Language :: Python :: 3.7
Classifier: Programming Language :: Python :: 3.8
Classifier: Programming Language :: Python :: 3.9
Classifier: Programming Language :: Python :: 3.10
Requires-Python: >=3.7
License-File: LICENSE
Requires-Dist: fire
Requires-Dist: PyYAML
Requires-Dist: kubernetes
Requires-Dist: rich
Requires-Dist: streamlit
Requires-Dist: pandas
Provides-Extra: dev
Requires-Dist: docformatter; extra == "dev"
Requires-Dist: black; extra == "dev"
Requires-Dist: isort; extra == "dev"
Requires-Dist: flake8; extra == "dev"
Requires-Dist: autoflake; extra == "dev"
Requires-Dist: sphinx; extra == "dev"
Requires-Dist: sphinx-rtd-theme; extra == "dev"
Requires-Dist: sphinx-autodoc-typehints; extra == "dev"
Requires-Dist: sphinx-material; extra == "dev"
